{
  "attributes": [
    {
      "default": "nil",
      "size": null,
      "type": "uuid",
      "source": "id",
      "references": null,
      "allow_nil?": false,
      "primary_key?": true,
      "generated?": false
    },
    {
      "default": "nil",
      "size": null,
      "type": "text",
      "source": "role",
      "references": null,
      "allow_nil?": true,
      "primary_key?": false,
      "generated?": false
    },
    {
      "default": "nil",
      "size": null,
      "type": "utc_datetime_usec",
      "source": "joined_at",
      "references": null,
      "allow_nil?": false,
      "primary_key?": false,
      "generated?": false
    },
    {
      "default": "nil",
      "size": null,
      "type": "utc_datetime_usec",
      "source": "inserted_at",
      "references": null,
      "allow_nil?": false,
      "primary_key?": false,
      "generated?": false
    },
    {
      "default": "nil",
      "size": null,
      "type": "utc_datetime_usec",
      "source": "updated_at",
      "references": null,
      "allow_nil?": false,
      "primary_key?": false,
      "generated?": false
    },
    {
      "default": "nil",
      "size": null,
      "type": "uuid",
      "source": "organization_id",
      "references": {
        "name": "memberships_organization_id_fkey",
        "table": "organizations",
        "multitenancy": {
          "global": null,
          "strategy": null,
          "attribute": null
        },
        "primary_key?": true,
        "destination_attribute": "id",
        "on_delete": null,
        "on_update": null,
        "deferrable": false,
        "destination_attribute_default": null,
        "destination_attribute_generated": null
      },
      "allow_nil?": true,
      "primary_key?": false,
      "generated?": false
    },
    {
      "default": "nil",
      "size": null,
      "type": "uuid",
      "source": "user_id",
      "references": {
        "name": "memberships_user_id_fkey",
        "table": "users",
        "multitenancy": {
          "global": null,
          "strategy": null,
          "attribute": null
        },
        "primary_key?": true,
        "destination_attribute": "id",
        "on_delete": null,
        "on_update": null,
        "deferrable": false,
        "destination_attribute_default": null,
        "destination_attribute_generated": null
      },
      "allow_nil?": true,
      "primary_key?": false,
      "generated?": false
    }
  ],
  "table": "memberships",
  "hash": "A8B426050262E3576CB0B3A8362726618BE251A77CD5CC9475AF5F63EC1A96B8",
  "multitenancy": {
    "global": false,
    "strategy": "attribute",
    "attribute": "organization_id"
  },
  "identities": [
    {
      "name": "unique_membership",
      "keys": [
        "user_id",
        "organization_id"
      ],
      "base_filter": null,
      "index_name": "memberships_unique_membership_index"
    }
  ],
  "repo": "Elixir.TaskManager.Repo",
  "strict?": false,
  "custom_indexes": [],
  "base_filter": null,
  "custom_statements": [],
  "has_create_action": true
}